torch_pba/__init__.py
torch_pba/__version__.py
torch_pba/_core/__init__.py
torch_pba/_core/_compute_Laplacian.py
torch_pba/_core/_compute_adjacency_matrix.py
torch_pba/_core/_compute_distance_matrix.py
torch_pba/_core/_compute_fate_bias.py
torch_pba/_core/_compute_mean_first_passage_time.py
torch_pba/_core/_compute_potential.py
torch_pba/_core/_configure_r.py
torch_pba/_core/_configure_s.py
torch_pba/_core/_construct_kNN_graph.py
torch_pba/_core/_torch_pba.py
torch_pba/_plotting/__init__.py
torch_pba/_plotting/_plot_fate_bias_clustermap.py
torch_pba/_utils/__init__.py
torch_pba/_utils/_downsample.py
torch_pba/_utils/_normalize.py
torch_pba/_utils/_pba_data.py
torch_pba-0.0.3.dist-info/LICENSE
torch_pba-0.0.3.dist-info/METADATA
torch_pba-0.0.3.dist-info/WHEEL
torch_pba-0.0.3.dist-info/top_level.txt
torch_pba-0.0.3.dist-info/RECORD
