Metadata-Version: 2.1
Name: torch-pba
Version: 0.0.3
Summary: PyTorch implementation of PBA.
Author: Michael E. Vinyard
Author-email: mvinyard.ai@gmail.com
License: MIT
Classifier: Development Status :: 2 - Pre-Alpha
Classifier: Programming Language :: Python :: 3.9
Classifier: Intended Audience :: Science/Research
Classifier: Topic :: Scientific/Engineering :: Bio-Informatics
Requires-Python: >3.9.0
License-File: LICENSE
Requires-Dist: adata-query >=0.0.1
Requires-Dist: anndata >=0.9.1
Requires-Dist: annoyance >=0.0.18
Requires-Dist: autodevice >=0.0.2
Requires-Dist: numpy ==1.22.3
Requires-Dist: seaborn >=0.12.2
Requires-Dist: torch >=2.0.1
